README.rst
setup.py
mongoUtils/__init__.py
mongoUtils/aggregation.py
mongoUtils/benchmarks.py
mongoUtils/bugs.py
mongoUtils/client.py
mongoUtils/configuration.py
mongoUtils/examples.py
mongoUtils/helpers.py
mongoUtils/importsExports.py
mongoUtils/mapreduce.py
mongoUtils/models.py
mongoUtils/pubsub.py
mongoUtils/schema.py
mongoUtils.egg-info/PKG-INFO
mongoUtils.egg-info/SOURCES.txt
mongoUtils.egg-info/dependency_links.txt
mongoUtils.egg-info/not-zip-safe
mongoUtils.egg-info/requires.txt
mongoUtils.egg-info/top_level.txt
mongoUtils/../MRjs/MapReduce.js
mongoUtils/../MRjs/misc.js
mongoUtils/../MRjs/tools.js
mongoUtils/../data/example_workbook.xlsx
mongoUtils/../data/muTest_tweets.json .gz
mongoUtils/importExport/__init__.py
mongoUtils/importExport/es.py
mongoUtils/importExport/excel.py
mongoUtils/tests/PubSubBench.py
mongoUtils/tests/__init__.py
mongoUtils/tests/tests.py
mongoUtils/tools/__init__.py
mongoUtils/tools/command.py
mongoUtils/tools/configuration.py
mongoUtils/tools/scripts.py