Metadata-Version: 1.1
Name: mongoUtils
Version: 1.1.8
Summary: Utilities for mongoDB mainly based on pymongo python mongoDB driver, see:http://github.com/mongodb/mongo-python-driver
Home-page: https://github.com/nickmilon/mongoUtils
Author: nickmilon
Author-email: nickmilon/gmail/com
License: MIT or Apache License, Version 2.0
Download-URL: https://github.com/nickmilon/mongoUtils.git
Keywords: mongo,mongodb,pymongo,mongo utilities,database,nosql,big data
Platform: UNKNOWN
Classifier: Development Status :: 5 - Production/Stable
Classifier: Intended Audience :: Developers
Classifier: License :: OSI Approved :: Apache Software License
Classifier: Operating System :: MacOS :: MacOS X
Classifier: Operating System :: Microsoft :: Windows
Classifier: Operating System :: POSIX
Classifier: Programming Language :: Python :: 2.7
Classifier: Programming Language :: Python :: 3.4
Classifier: Topic :: Database
